koroviev/__init__.py
koroviev/__main__.py
koroviev/cli.py
koroviev/components/__init__.py
koroviev/components/project.py
koroviev/components/structure.py
koroviev/components/templates.py
koroviev/const.py
koroviev/enums.py
koroviev/models.py
koroviev/utils.py
koroviev-0.1.21.dist-info/entry_points.txt
koroviev-0.1.21.dist-info/WHEEL
koroviev-0.1.21.dist-info/METADATA
koroviev-0.1.21.dist-info/RECORD
